game_2048/__init__.py
game_2048/block.py
game_2048/button.py
game_2048/game.py
game_2048/game_function.py
game_2048/information.py
game_2048/number.py
game_2048/scoreboard.py
game_2048/settings.py
game_2048/tips.py
game_2048/fonts/AmericanTypewriter.TTF
game_2048/fonts/STXINGKA.TTF
game_2048/fonts/__init__.py
game_2048/image/0.png
game_2048/image/1024.png
game_2048/image/128.png
game_2048/image/16.png
game_2048/image/2.png
game_2048/image/2048.png
game_2048/image/256.png
game_2048/image/32.png
game_2048/image/4.png
game_2048/image/512.png
game_2048/image/64.png
game_2048/image/8.png
game_2048/image/__init__.py
game_2048/image/best_score.png
game_2048/image/bt_bg.png
game_2048/image/exit.png
game_2048/image/now_score.png
game_2048/image/reset.png
game_2048/image/roll_back.png
game_2048/image/roll_back_unable.png
game_2048/image/save.png
game_2048/image/screen_shot.png
pygame_2048-1.9.4.dist-info/LICENSE
pygame_2048-1.9.4.dist-info/METADATA
pygame_2048-1.9.4.dist-info/WHEEL
pygame_2048-1.9.4.dist-info/entry_points.txt
pygame_2048-1.9.4.dist-info/top_level.txt
pygame_2048-1.9.4.dist-info/RECORD
