Metadata-Version: 1.1
Name: pygame-2048
Version: 1.9.4
Summary: A 2048 game 
Home-page: https://github.com/dzc217/game_2048
Author: Dai Zhengcheng
Author-email: dzcheng827@gmail.com
License: MIT License
Platform: UNKNOWN
Classifier: Topic :: Games/Entertainment :: Puzzle Games
Classifier: Programming Language :: Python :: 3 :: Only
Classifier: Programming Language :: Python :: 3.9
Classifier: Development Status :: 5 - Production/Stable
Classifier: License :: OSI Approved :: MIT License
Classifier: Natural Language :: English
